vpx_rtp/__init__.py
vpx_rtp/clock.py
vpx_rtp/codecs/_vpx.cpython-310-x86_64-linux-gnu.so
vpx_rtp/codecs/_vpx.o
vpx_rtp/codecs/_vpx.pyi
vpx_rtp/codecs/vpx.py
vpx_rtp/jitterbuffer.py
vpx_rtp/py.typed
vpx_rtp/received_rtp_stream_statistics.py
vpx_rtp/rtcrtpparameters.py
vpx_rtp/rtp.py
vpx_rtp/test.py
vpx_rtp/utils.py
vpx_rtp_py-0.5.0.dist-info/LICENSE
vpx_rtp_py-0.5.0.dist-info/METADATA
vpx_rtp_py-0.5.0.dist-info/WHEEL
vpx_rtp_py-0.5.0.dist-info/entry_points.txt
vpx_rtp_py-0.5.0.dist-info/RECORD
