Metadata-Version: 2.1
Name: vpx-rtp-py
Version: 0.5.0
Summary: lightweight python interface for generating rtp streams using vpx codecs
License: MIT
Author: Josh Gruenstein
Author-email: josh@tutorintelligence.com
Requires-Python: >=3.10,<4.0
Classifier: License :: OSI Approved :: MIT License
Classifier: Programming Language :: Python :: 3
Classifier: Programming Language :: Python :: 3.10
Classifier: Programming Language :: Python :: 3.11
Classifier: Programming Language :: Python :: 3.12
Classifier: Programming Language :: Python :: 3.13
Requires-Dist: av (>=12.1.0)
